odoo/addons/product_country_of_origin/LICENSE
odoo/addons/product_country_of_origin/README.rst
odoo/addons/product_country_of_origin/__init__.py
odoo/addons/product_country_of_origin/__manifest__.py
odoo/addons/product_country_of_origin/images/screen.png
odoo/addons/product_country_of_origin/models/__init__.py
odoo/addons/product_country_of_origin/models/product_template.py
odoo/addons/product_country_of_origin/static/description/icon.png
odoo/addons/product_country_of_origin/static/description/index.html
odoo/addons/product_country_of_origin/tests/TEST_INSTRUCTIONS.rst
odoo/addons/product_country_of_origin/views/product_template.xml
odoo_addon_product_country_of_origin-16.0.1.0.0.dist-info/METADATA
odoo_addon_product_country_of_origin-16.0.1.0.0.dist-info/WHEEL
odoo_addon_product_country_of_origin-16.0.1.0.0.dist-info/top_level.txt
odoo_addon_product_country_of_origin-16.0.1.0.0.dist-info/RECORD
